{
    "fluentMethods": true,
    "relationships": [
        {
            "relationshipType": "many-to-one",
            "relationshipName": "customer",
            "otherEntityName": "customer",
            "otherEntityField": "id"
        }
    ],
    "fields": [
        {
            "fieldName": "address1",
            "fieldType": "String"
        },
        {
            "fieldName": "address2",
            "fieldType": "String"
        },
        {
            "fieldName": "city",
            "fieldType": "String"
        },
        {
            "fieldName": "postcode",
            "fieldType": "String",
            "fieldValidateRules": [
                "required",
                "maxlength"
            ],
            "fieldValidateRulesMaxlength": 10
        },
        {
            "fieldName": "country",
            "fieldType": "String",
            "fieldValidateRules": [
                "required",
                "maxlength"
            ],
            "fieldValidateRulesMaxlength": 2
        }
    ],
    "changelogDate": "20180527152144",
    "entityTableName": "address",
    "dto": "no",
    "pagination": "pager",
    "service": "no",
    "jpaMetamodelFiltering": false
}